apexpy/__init__.py
apexpy/api.py
apexpy/characters.py
apexpy/exceptions.py
apexpy/httprequest.py
apexpy/utils.py
apexlegendspy-0.0.2.dist-info/LICENSE.md
apexlegendspy-0.0.2.dist-info/METADATA
apexlegendspy-0.0.2.dist-info/WHEEL
apexlegendspy-0.0.2.dist-info/top_level.txt
apexlegendspy-0.0.2.dist-info/RECORD
