Metadata-Version: 2.1
Name: apexlegendspy
Version: 0.0.2
Summary: Apex-legends api async wrapper
Home-page: https://github.com/surister/apexpy
Author: surister
Author-email: surister98@gmail.com
License: MIT
Platform: UNKNOWN
Classifier: Programming Language :: Python :: 3
Classifier: License :: OSI Approved :: MIT License
Classifier: Operating System :: OS Independent
Classifier: Topic :: Utilities
Requires-Python: >=3.6.0
Requires-Dist: aiohttp
